{
	"info": {
		"_postman_id": "73df1224-1ba8-4881-8d38-8bb108fa6550",
		"name": "NestJS",
		"schema": "https://schema.getpostman.com/json/collection/v2.1.0/collection.json",
		"_exporter_id": "15072037"
	},
	"item": [
		{
			"name": "Create a New User",
			"request": {
				"method": "POST",
				"header": [],
				"body": {
					"mode": "raw",
					"raw": "{\r\n    \"name\": \"Dwayne Johnson\",\r\n    \"username\": \"dwaynetherock\",\r\n    \"email\": \"dwayne@therock.com\",\r\n    \"password\": \"dwayne@123\"\r\n}",
					"options": {
						"raw": {
							"language": "json"
						}
					}
				},
				"url": {
					"raw": "{{url}}/users",
					"host": [
						"{{url}}"
					],
					"path": [
						"users"
					]
				}
			},
			"response": []
		},
		{
			"name": "Login User",
			"request": {
				"method": "POST",
				"header": [],
				"body": {
					"mode": "raw",
					"raw": "{\r\n    \"email\": \"dwayne@therock.com\",\r\n    \"password\": \"dwayne@123\"\r\n}",
					"options": {
						"raw": {
							"language": "json"
						}
					}
				},
				"url": {
					"raw": "{{url}}/users/login",
					"host": [
						"{{url}}"
					],
					"path": [
						"users",
						"login"
					]
				}
			},
			"response": []
		},
		{
			"name": "Update User By Id",
			"request": {
				"method": "PUT",
				"header": [],
				"body": {
					"mode": "raw",
					"raw": "{\r\n    \"name\": \"Dwayne Johnson\",\r\n    \"username\": \"dwayne_the_rock\"\r\n}",
					"options": {
						"raw": {
							"language": "json"
						}
					}
				},
				"url": {
					"raw": "{{url}}/users/2",
					"host": [
						"{{url}}"
					],
					"path": [
						"users",
						"2"
					]
				}
			},
			"response": []
		},
		{
			"name": "Get All Users",
			"protocolProfileBehavior": {
				"disableBodyPruning": true
			},
			"request": {
				"method": "GET",
				"header": [],
				"body": {
					"mode": "raw",
					"raw": "{\r\n    \"name\": \"James Fort\",\r\n    \"username\": \"fortknight\"\r\n}",
					"options": {
						"raw": {
							"language": "json"
						}
					}
				},
				"url": {
					"raw": "{{url}}/users",
					"host": [
						"{{url}}"
					],
					"path": [
						"users"
					]
				}
			},
			"response": []
		},
		{
			"name": "Get User By Id",
			"protocolProfileBehavior": {
				"disableBodyPruning": true
			},
			"request": {
				"method": "GET",
				"header": [],
				"body": {
					"mode": "raw",
					"raw": "{\r\n    \"name\": \"James Fort\",\r\n    \"username\": \"fortknight\"\r\n}",
					"options": {
						"raw": {
							"language": "json"
						}
					}
				},
				"url": {
					"raw": "{{url}}/users/2",
					"host": [
						"{{url}}"
					],
					"path": [
						"users",
						"2"
					]
				}
			},
			"response": []
		},
		{
			"name": "Delete User by ID",
			"request": {
				"method": "DELETE",
				"header": [],
				"body": {
					"mode": "raw",
					"raw": "{\r\n    \"name\": \"James Fort\",\r\n    \"username\": \"fortknight\"\r\n}",
					"options": {
						"raw": {
							"language": "json"
						}
					}
				},
				"url": {
					"raw": "{{url}}/users/1",
					"host": [
						"{{url}}"
					],
					"path": [
						"users",
						"1"
					]
				}
			},
			"response": []
		}
	],
	"event": [
		{
			"listen": "prerequest",
			"script": {
				"type": "text/javascript",
				"exec": [
					""
				]
			}
		},
		{
			"listen": "test",
			"script": {
				"type": "text/javascript",
				"exec": [
					""
				]
			}
		}
	],
	"variable": [
		{
			"key": "url",
			"value": "http://localhost:3000",
			"type": "string"
		}
	]
}